veriscore/__init__.py
veriscore/claim_extractor.py
veriscore/claim_verifier.py
veriscore/extract_claims.py
veriscore/get_response.py
veriscore/retrieve_evidence.py
veriscore/search_API.py
veriscore/utils.py
veriscore/verify_claims.py
veriscore/veriscore.py
VeriScore-2.0.3.dist-info/LICENSE
VeriScore-2.0.3.dist-info/METADATA
VeriScore-2.0.3.dist-info/WHEEL
VeriScore-2.0.3.dist-info/top_level.txt
VeriScore-2.0.3.dist-info/RECORD
