Metadata-Version: 2.1
Name: VeriScore
Version: 2.0.3
Summary: Pip package for VeriScore
License: UNKNOWN
Platform: UNKNOWN
Classifier: Programming Language :: Python :: 3
Classifier: License :: OSI Approved :: MIT License
Classifier: Operating System :: OS Independent
Requires-Python: >=3.9
License-File: LICENSE
Requires-Dist: spacy
Requires-Dist: openai
Requires-Dist: anthropic
Requires-Dist: tiktoken
Requires-Dist: tqdm
